pymymusic/__init__.py
pymymusic/pymymusic.py
pymymusic-0.0.1.dist-info/METADATA
pymymusic-0.0.1.dist-info/WHEEL
pymymusic-0.0.1.dist-info/top_level.txt
pymymusic-0.0.1.dist-info/RECORD
